{
  "91d912a0af73242f19bc248485203636e3bdd71a": {
    "input": "人间钱话",
    "status": "not_found",
    "podcast_id": "",
    "selected_url": "",
    "selected_title": "",
    "min_score": 0.86,
    "min_gap": 0.05,
    "candidates": [],
    "from_cache": false,
    "resolved_at": "2026-03-05 17:57:16"
  },
  "c9f4d6bde17b9d3f2ad44c4c368198adb00dfae9": {
    "input": "深度求真",
    "status": "not_found",
    "podcast_id": "",
    "selected_url": "",
    "selected_title": "",
    "min_score": 0.86,
    "min_gap": 0.05,
    "candidates": [],
    "from_cache": false,
    "resolved_at": "2026-03-05 17:57:26"
  },
  "597ead58d191af966075407e2d342db87a3da419": {
    "input": "德邦基金财经列车",
    "status": "not_found",
    "podcast_id": "",
    "selected_url": "",
    "selected_title": "",
    "min_score": 0.86,
    "min_gap": 0.05,
    "candidates": [],
    "from_cache": false,
    "resolved_at": "2026-03-05 17:57:35"
  },
  "66cb108891e1ca7457f371794a5890900a05550e": {
    "input": "茶水间经济学",
    "status": "not_found",
    "podcast_id": "",
    "selected_url": "",
    "selected_title": "",
    "min_score": 0.86,
    "min_gap": 0.05,
    "candidates": [],
    "from_cache": false,
    "resolved_at": "2026-03-05 17:57:46"
  },
  "93a4b25d5e6df70d9dfa6072cf761285cf321dff": {
    "input": "随基漫步",
    "status": "not_found",
    "podcast_id": "",
    "selected_url": "",
    "selected_title": "",
    "min_score": 0.86,
    "min_gap": 0.05,
    "candidates": [],
    "from_cache": false,
    "resolved_at": "2026-03-05 17:57:55"
  },
  "985747c47a7f477384b1400e73aa048d58adff4a": {
    "input": "莫问钱程",
    "status": "not_found",
    "podcast_id": "",
    "selected_url": "",
    "selected_title": "",
    "min_score": 0.86,
    "min_gap": 0.05,
    "candidates": [],
    "from_cache": false,
    "resolved_at": "2026-03-05 17:58:08"
  },
  "5ced6b928f75a0aeb7933f813a32ac4b8e1df923": {
    "input": "泰客Talk",
    "status": "not_found",
    "podcast_id": "",
    "selected_url": "",
    "selected_title": "",
    "min_score": 0.86,
    "min_gap": 0.05,
    "candidates": [],
    "from_cache": false,
    "resolved_at": "2026-03-05 17:58:19"
  },
  "106ccf0afb900239b98a311e867d7ccc5e13b6e5": {
    "input": "时间嘉讲",
    "status": "not_found",
    "podcast_id": "",
    "selected_url": "",
    "selected_title": "",
    "min_score": 0.86,
    "min_gap": 0.05,
    "candidates": [],
    "from_cache": false,
    "resolved_at": "2026-03-05 17:58:30"
  },
  "8600cf80f1d688c4617b17c7a4d89d43c36122d5": {
    "input": "财话连篇",
    "status": "not_found",
    "podcast_id": "",
    "selected_url": "",
    "selected_title": "",
    "min_score": 0.86,
    "min_gap": 0.05,
    "candidates": [],
    "from_cache": false,
    "resolved_at": "2026-03-05 17:58:38"
  },
  "80f00e08731113ebf9a6971eb2b3f7de91116cc9": {
    "input": "养基方程式",
    "status": "not_found",
    "podcast_id": "",
    "selected_url": "",
    "selected_title": "",
    "min_score": 0.86,
    "min_gap": 0.05,
    "candidates": [],
    "from_cache": false,
    "resolved_at": "2026-03-05 17:58:53"
  },
  "53a08137a282fbd6b9e816cb376398de6988099f": {
    "input": "好朋友的播客",
    "status": "not_found",
    "podcast_id": "",
    "selected_url": "",
    "selected_title": "",
    "min_score": 0.86,
    "min_gap": 0.05,
    "candidates": [],
    "from_cache": false,
    "resolved_at": "2026-03-05 17:59:02"
  },
  "ab0e0bd651a603c3d9ea75866b8a1899486da113": {
    "input": "钱途规划局",
    "status": "not_found",
    "podcast_id": "",
    "selected_url": "",
    "selected_title": "",
    "min_score": 0.86,
    "min_gap": 0.05,
    "candidates": [],
    "from_cache": false,
    "resolved_at": "2026-03-05 17:59:13"
  },
  "ba4e123b7f265b4cc0ec59ee041cec953a631230": {
    "input": "好朋友的直播间",
    "status": "not_found",
    "podcast_id": "",
    "selected_url": "",
    "selected_title": "",
    "min_score": 0.86,
    "min_gap": 0.05,
    "candidates": [],
    "from_cache": false,
    "resolved_at": "2026-03-05 17:59:21"
  },
  "3357e4feaa0663a924286b7f366d6d55a5847b9b": {
    "input": "投资心法·基金访谈录",
    "status": "not_found",
    "podcast_id": "",
    "selected_url": "",
    "selected_title": "",
    "min_score": 0.86,
    "min_gap": 0.05,
    "candidates": [],
    "from_cache": false,
    "resolved_at": "2026-03-05 17:59:32"
  },
  "3211a7ee6eb97fe524eb99f3e2df009fca3b6c79": {
    "input": "投资心得·基金聊天局",
    "status": "not_found",
    "podcast_id": "",
    "selected_url": "",
    "selected_title": "",
    "min_score": 0.86,
    "min_gap": 0.05,
    "candidates": [],
    "from_cache": false,
    "resolved_at": "2026-03-05 17:59:42"
  },
  "cc7059337d9350baba9f8b0fc0e1264d4a996c66": {
    "input": "与财同行",
    "status": "not_found",
    "podcast_id": "",
    "selected_url": "",
    "selected_title": "",
    "min_score": 0.86,
    "min_gap": 0.05,
    "candidates": [],
    "from_cache": false,
    "resolved_at": "2026-03-05 17:59:53"
  },
  "2bbc5cd6c3ffda8a8f8984b54d25b1ea59200941": {
    "input": "鹏然心动",
    "status": "not_found",
    "podcast_id": "",
    "selected_url": "",
    "selected_title": "",
    "min_score": 0.86,
    "min_gap": 0.05,
    "candidates": [],
    "from_cache": false,
    "resolved_at": "2026-03-05 18:00:01"
  },
  "da70dde60b998b029b26a01ff83a5bcbefe14e15": {
    "input": "基金经理一周论市",
    "status": "not_found",
    "podcast_id": "",
    "selected_url": "",
    "selected_title": "",
    "min_score": 0.86,
    "min_gap": 0.05,
    "candidates": [],
    "from_cache": false,
    "resolved_at": "2026-03-05 18:00:15"
  }
}